tuya_iot/__init__.py
tuya_iot/asset.py
tuya_iot/device.py
tuya_iot/home.py
tuya_iot/infrared.py
tuya_iot/openapi.py
tuya_iot/openlogging.py
tuya_iot/openmq.py
tuya_iot/tuya_enums.py
tuya_iot/version.py
tuya_iot_py_sdk-0.6.6.dist-info/LICENSE
tuya_iot_py_sdk-0.6.6.dist-info/METADATA
tuya_iot_py_sdk-0.6.6.dist-info/WHEEL
tuya_iot_py_sdk-0.6.6.dist-info/entry_points.txt
tuya_iot_py_sdk-0.6.6.dist-info/top_level.txt
tuya_iot_py_sdk-0.6.6.dist-info/RECORD
