Metadata-Version: 2.1
Name: tuya-iot-py-sdk
Version: 0.6.6
Summary: A Python sdk for Tuya Open API, which provides IoT capabilities, maintained by Tuya official
Home-page: https://github.com/tuya/tuya-iot-app-sdk-python
Author: Tuya Inc.
Author-email: developer@tuya.com
License: MIT
Project-URL: Bug Tracker, https://github.com/tuya/tuya-iot-app-sdk-python/issues
Project-URL: Changes, https://github.com/tuya/tuya-iot-python-sdk/wiki/Tuya-IoT-Python-SDK-Release-Notes
Keywords: tuya iot app sdk python
Platform: UNKNOWN
Classifier: Development Status :: 4 - Beta
Classifier: License :: OSI Approved :: MIT License
Classifier: Operating System :: OS Independent
Classifier: Topic :: Software Development
Classifier: Programming Language :: Python :: 3
Classifier: Programming Language :: Python :: 3.7
Classifier: Programming Language :: Python :: 3.8
Classifier: Programming Language :: Python :: 3.9
Classifier: Programming Language :: Python :: 3.10
Classifier: Programming Language :: Python :: Implementation :: PyPy
Requires-Python: >=3.7
